ka_uts_log/__init__.py
ka_uts_log/__version__.py
ka_uts_log/log.py
ka_uts_log/py.typed
ka_uts_log/utils.py
ka_uts_log/cfg/__init__.py
ka_uts_log/cfg/log.std.yml
ka_uts_log/cfg/log.usr.yml
ka_uts_log-4.1.1.250609.dist-info/licenses/LICENSE.txt
ka_uts_log-4.1.1.250609.dist-info/METADATA
ka_uts_log-4.1.1.250609.dist-info/WHEEL
ka_uts_log-4.1.1.250609.dist-info/top_level.txt
ka_uts_log-4.1.1.250609.dist-info/RECORD
