Metadata-Version: 2.4
Name: ka_uts_log
Version: 4.1.1.250609
Summary: Logging Utilities
Author-email: Bernd Stroehle <bernd.stroehle@gmail.com>
Maintainer-email: Bernd Stroehle <bernd.stroehle@gmail.com>
License-Expression: GPL-3.0-only WITH Classpath-exception-2.0 OR BSD-3-Clause
Project-URL: Source Code, https://github.com/bs291048/ka_uts_log/tree/master
Project-URL: Homepage, https://kosakya.de/
Project-URL: Documentation, https://ka-com.readthedocs.io/en/latest
Classifier: Development Status :: 5 - Production/Stable
Classifier: Intended Audience :: Developers
Classifier: Operating System :: OS Independent
Classifier: Programming Language :: Python :: 3.11
Classifier: Natural Language :: English
Classifier: Topic :: Software Development :: Libraries :: Python Modules
Requires-Python: >=3.10
License-File: LICENSE.txt
Requires-Dist: ka_uts_uts>=4.1.0.250601
Requires-Dist: psutil>=7.0.0
Requires-Dist: pytz>=2025.1
Dynamic: license-file
